tsb_tools_core/__init__.py
tsb_tools_core/app.py
tsb_tools_core/cli.py
tsb_tools_core/utils/paths.py
tsb_tools_core-0.1.1.dist-info/METADATA
tsb_tools_core-0.1.1.dist-info/WHEEL
tsb_tools_core-0.1.1.dist-info/entry_points.txt
tsb_tools_core-0.1.1.dist-info/top_level.txt
tsb_tools_core-0.1.1.dist-info/RECORD
