Metadata-Version: 2.4
Name: tsb-tools-core
Version: 0.1.1
Summary: sudoblock CLI tools
License: Closed Source / Do not distribute.
Requires-Dist: typer
Requires-Dist: jinja2
Requires-Dist: git-cliff
Requires-Dist: semver
Requires-Dist: PyGithub
Provides-Extra: dev
Requires-Dist: pytest; extra == "dev"
Requires-Dist: pytest-mock; extra == "dev"
Provides-Extra: tackle
Requires-Dist: tackle; extra == "tackle"
